OpenLibrary/__init__.py
ralfi-0.1.0.dist-info/METADATA
ralfi-0.1.0.dist-info/WHEEL
ralfi-0.1.0.dist-info/top_level.txt
ralfi-0.1.0.dist-info/RECORD
