Metadata-Version: 2.4
Name: ralfi
Version: 0.1.0
Summary: Library Python abal-abal
Author: Nama Kamu
Author-email: email@contoh.com
Classifier: Programming Language :: Python :: 3
Classifier: License :: OSI Approved :: MIT License
Requires-Python: >=3.6
Dynamic: author
Dynamic: author-email
Dynamic: classifier
Dynamic: description
Dynamic: description-content-type
Dynamic: requires-python
Dynamic: summary
